./.gitignore
./CHANGELOG.md
./LICENSE
./Makefile
./PKG-INFO
./README.md
./__init__.py
./decorators.py
./logger.py
./py.typed
./pyproject.toml
./renderer.py
./docs/API.md
./docs/CONTRIBUTING.md
./examples/basic.py
./examples/cli_app.py
./examples/custom_renderer.py
./examples/logger_usage.py
./examples/logging.py
./tests/__init__.py
./tests/test_core.py
./tests/test_decorators.py
./tests/test_logger.py
./tests/test_renderer.py
clickmd-1.0.0.dist-info/METADATA
clickmd-1.0.0.dist-info/WHEEL
clickmd-1.0.0.dist-info/licenses/LICENSE
clickmd-1.0.0.dist-info/RECORD
