Metadata-Version: 2.4
Name: clickmd
Version: 1.0.0
Summary: Markdown rendering for CLI applications with syntax highlighting
Project-URL: Homepage, https://github.com/wronai/clickmd
Project-URL: Documentation, https://github.com/wronai/clickmd#readme
Project-URL: Repository, https://github.com/wronai/clickmd
Project-URL: Issues, https://github.com/wronai/clickmd/issues
Author-email: Reclapp Team <contact@reclapp.io>
License-Expression: MIT
License-File: LICENSE
Keywords: ansi,cli,colors,markdown,syntax-highlighting,terminal
Classifier: Development Status :: 4 - Beta
Classifier: Environment :: Console
Classifier: Intended Audience :: Developers
Classifier: License :: OSI Approved :: MIT License
Classifier: Operating System :: OS Independent
Classifier: Programming Language :: Python :: 3
Classifier: Programming Language :: Python :: 3.10
Classifier: Programming Language :: Python :: 3.11
Classifier: Programming Language :: Python :: 3.12
Classifier: Programming Language :: Python :: 3.13
Classifier: Topic :: Software Development :: Libraries :: Python Modules
Classifier: Topic :: Terminals
Classifier: Typing :: Typed
Requires-Python: >=3.10
Provides-Extra: all
Requires-Dist: black>=23.0; extra == 'all'
Requires-Dist: click>=8.0; extra == 'all'
Requires-Dist: mypy>=1.0; extra == 'all'
Requires-Dist: pytest-cov>=4.0; extra == 'all'
Requires-Dist: pytest>=7.0; extra == 'all'
Requires-Dist: ruff>=0.1.0; extra == 'all'
Provides-Extra: click
Requires-Dist: click>=8.0; extra == 'click'
Provides-Extra: dev
Requires-Dist: black>=23.0; extra == 'dev'
Requires-Dist: mypy>=1.0; extra == 'dev'
Requires-Dist: pytest-cov>=4.0; extra == 'dev'
Requires-Dist: pytest>=7.0; extra == 'dev'
Requires-Dist: ruff>=0.1.0; extra == 'dev'
